pragmatic_blackjack/__init__.py
pragmatic_blackjack/event.py
pragmatic_blackjack/exceptions.py
pragmatic_blackjack/handler.py
pragmatic_blackjack/seat.py
pragmatic_blackjack/table.py
pragmatic_blackjack/websocket.py
pragmatic_blackjack-2.0.19.dist-info/LICENSE
pragmatic_blackjack-2.0.19.dist-info/METADATA
pragmatic_blackjack-2.0.19.dist-info/WHEEL
pragmatic_blackjack-2.0.19.dist-info/RECORD
