Metadata-Version: 2.3
Name: pragmatic-blackjack
Version: 2.0.19
Summary: Play on Pragmatic Play Blackjack tables through Python.
Author: Zachary Hampton
Author-email: zachary@bunsly.com
Requires-Python: >=3.10,<4.0
Classifier: Programming Language :: Python :: 3
Classifier: Programming Language :: Python :: 3.10
Classifier: Programming Language :: Python :: 3.11
Classifier: Programming Language :: Python :: 3.12
Classifier: Programming Language :: Python :: 3.13
Requires-Dist: pydantic (>=2.10.6,<3.0.0)
Requires-Dist: requests (>=2.32.3,<3.0.0)
Requires-Dist: websockets (>=12.0,<13.0)
Requires-Dist: xmltodict (>=0.13.0,<0.14.0)
